agentic_commands_stego/README.md
agentic_commands_stego/__init__.py
agentic_commands_stego/requirements.txt
agentic_commands_stego/simple_test.py
agentic_commands_stego/test_mcp_cli.py
agentic_commands_stego/test_mcp_integration.py
agentic_commands_stego/test_video_functionality.py
agentic_commands_stego/working_test.py
agentic_commands_stego/__pycache__/__init__.cpython-312.opt-1.pyc
agentic_commands_stego/__pycache__/__init__.cpython-312.pyc
agentic_commands_stego/__pycache__/simple_test.cpython-312.opt-1.pyc
agentic_commands_stego/__pycache__/simple_test.cpython-312.pyc
agentic_commands_stego/__pycache__/test_mcp_cli.cpython-312.opt-1.pyc
agentic_commands_stego/__pycache__/test_mcp_cli.cpython-312.pyc
agentic_commands_stego/__pycache__/test_mcp_integration.cpython-312.opt-1.pyc
agentic_commands_stego/__pycache__/test_mcp_integration.cpython-312.pyc
agentic_commands_stego/__pycache__/test_video_functionality.cpython-312.opt-1.pyc
agentic_commands_stego/__pycache__/test_video_functionality.cpython-312.pyc
agentic_commands_stego/__pycache__/working_test.cpython-312.opt-1.pyc
agentic_commands_stego/__pycache__/working_test.cpython-312.pyc
agentic_commands_stego/crypto/__init__.py
agentic_commands_stego/crypto/cipher.py
agentic_commands_stego/crypto/__pycache__/__init__.cpython-312.opt-1.pyc
agentic_commands_stego/crypto/__pycache__/__init__.cpython-312.pyc
agentic_commands_stego/crypto/__pycache__/cipher.cpython-312.opt-1.pyc
agentic_commands_stego/crypto/__pycache__/cipher.cpython-312.pyc
agentic_commands_stego/decode/__init__.py
agentic_commands_stego/decode/audio_decoder.py
agentic_commands_stego/decode/ultrasonic_decoder.py
agentic_commands_stego/decode/video_decoder.py
agentic_commands_stego/decode/__pycache__/__init__.cpython-312.opt-1.pyc
agentic_commands_stego/decode/__pycache__/__init__.cpython-312.pyc
agentic_commands_stego/decode/__pycache__/audio_decoder.cpython-312.opt-1.pyc
agentic_commands_stego/decode/__pycache__/audio_decoder.cpython-312.pyc
ultrasonic_agentics-1.0.1.dist-info/licenses/LICENSE
ultrasonic_agentics-1.0.1.dist-info/METADATA
ultrasonic_agentics-1.0.1.dist-info/WHEEL
ultrasonic_agentics-1.0.1.dist-info/entry_points.txt
ultrasonic_agentics-1.0.1.dist-info/top_level.txt
ultrasonic_agentics-1.0.1.dist-info/RECORD
